fast_youtube_search/__init__.py
fast_youtube_search/search.py
fast_youtube_search/search_alt.py
fast_youtube_search-0.0.8.dist-info/LICENSE
fast_youtube_search-0.0.8.dist-info/METADATA
fast_youtube_search-0.0.8.dist-info/WHEEL
fast_youtube_search-0.0.8.dist-info/top_level.txt
fast_youtube_search-0.0.8.dist-info/RECORD
