Metadata-Version: 2.1
Name: fast_youtube_search
Version: 0.0.8
Summary: Unlimited youtube search with web scrapping
Home-page: https://github.com/andrscyv/fast_youtube_search
Author: Andres Cruz y Vera
Author-email: andrscyv@gmail.com
License: UNKNOWN
Platform: UNKNOWN
Classifier: Programming Language :: Python :: 3
Classifier: License :: OSI Approved :: MIT License
Classifier: Operating System :: OS Independent
Requires-Python: >=3.6
